esquilax/__init__.py
esquilax/batch_runner.py
esquilax/ml/__init__.py
esquilax/ml/evo/__init__.py
esquilax/ml/evo/strategy.py
esquilax/ml/evo/training.py
esquilax/ml/evo/tree_utils.py
esquilax/ml/evo/types.py
esquilax/ml/rl/__init__.py
esquilax/ml/rl/agent.py
esquilax/ml/rl/agent_state.py
esquilax/ml/rl/environment.py
esquilax/ml/rl/training.py
esquilax/ml/rl/tree_utils.py
esquilax/ml/rl/types.py
esquilax/ml/updates.py
esquilax/py.typed
esquilax/reductions.py
esquilax/runner.py
esquilax/sim.py
esquilax/transforms/__init__.py
esquilax/transforms/_graph.py
esquilax/transforms/_grid.py
esquilax/transforms/_map.py
esquilax/transforms/_space.py
esquilax/typing.py
esquilax/utils/__init__.py
esquilax/utils/functions.py
esquilax/utils/graph.py
esquilax/utils/space.py
esquilax/utils/tree.py
esquilax-2.1.0.dist-info/LICENSE.txt
esquilax-2.1.0.dist-info/METADATA
esquilax-2.1.0.dist-info/WHEEL
esquilax-2.1.0.dist-info/RECORD
