Metadata-Version: 2.1
Name: esquilax
Version: 2.1.0
Summary: JAX multi-agent simulation and ML toolset
Home-page: https://zombie-einstein.github.io/esquilax
License: MIT
Keywords: agent-based modelling,simulation,reinforcement-learning
Author: Zombie-Einstein
Author-email: zombie-einstein@proton.me
Requires-Python: >=3.10,<4.0
Classifier: Development Status :: 4 - Beta
Classifier: Environment :: GPU
Classifier: Intended Audience :: Science/Research
Classifier: License :: OSI Approved :: MIT License
Classifier: Programming Language :: Python
Classifier: Programming Language :: Python :: 3
Classifier: Programming Language :: Python :: 3.10
Classifier: Programming Language :: Python :: 3.11
Classifier: Programming Language :: Python :: 3.12
Classifier: Programming Language :: Python :: Implementation :: CPython
Classifier: Programming Language :: Python :: Implementation :: PyPy
Classifier: Topic :: Scientific/Engineering :: Artificial Intelligence
Classifier: Topic :: Scientific/Engineering :: Artificial Life
Provides-Extra: all
Provides-Extra: evo
Provides-Extra: rl
Requires-Dist: chex (>=0.1.3)
Requires-Dist: evosax (>=0.1.6,<0.2.0) ; extra == "evo" or extra == "all"
Requires-Dist: flax (>=0.10.0,<0.11.0) ; extra == "rl" or extra == "all"
Requires-Dist: jax (>=0.4.30)
Requires-Dist: jax-tqdm (>=0.3.1)
Project-URL: Documentation, https://zombie-einstein.github.io/esquilax
Project-URL: Repository, https://github.com/zombie-einstein/esquilax
